README.md
setup.py
rps_databases/__init__.py
rps_databases/common.py
rps_databases/database.py
rps_databases/operators.py
rps_databases/where_builder.py
rps_databases.egg-info/PKG-INFO
rps_databases.egg-info/SOURCES.txt
rps_databases.egg-info/dependency_links.txt
rps_databases.egg-info/requires.txt
rps_databases.egg-info/top_level.txt