Metadata-Version: 2.1
Name: rps-databases
Version: 0.2.2
Summary: Funções para conexão com banco de dados
Home-page: https://github.com/rpscapital/rps-databases
Author: Wilian Silva
Author-email: wilianzilv@gmail.com
Requires-Python: >=3.5.2
